setup.py
RogotoParser.egg-info/PKG-INFO
RogotoParser.egg-info/SOURCES.txt
RogotoParser.egg-info/dependency_links.txt
RogotoParser.egg-info/top_level.txt
rogoto/__init__.py
rogoto/parser.py
test/__init__.py
test/test_parser.py