Metadata-Version: 1.0
Name: RogotoParser
Version: 0.1
Summary: A parser of Rogoto Commands
Home-page: https://github.com/AutomatedTester/rogoto-py
Author: David Burns
Author-email: david.burns@theautomatedtester.co.uk
License: UNKNOWN
Platform: UNKNOWN
